MANIFEST.in
README.md
setup.py
bread_mail/__init__.py
bread_mail/function.py
bread_mail/gui.py
bread_mail/main.py
bread_mail/tempCodeRunnerFile.py
bread_mail.egg-info/PKG-INFO
bread_mail.egg-info/SOURCES.txt
bread_mail.egg-info/dependency_links.txt
bread_mail.egg-info/not-zip-safe
bread_mail.egg-info/requires.txt
bread_mail.egg-info/top_level.txt
bread_mail/assets/button_1.png
bread_mail/assets/button_2.png
bread_mail/assets/button_4.png
bread_mail/assets/button_5.png
bread_mail/assets/button_6.png
bread_mail/assets/button_7.png
bread_mail/assets/button_8.png
bread_mail/assets/entry_1.png
bread_mail/assets/entry_2.png
bread_mail/assets/entry_3.png
bread_mail/assets/entry_4.png
bread_mail/assets/entry_5.png
bread_mail/assets/entry_6.png
bread_mail/assets/image_1.png
bread_mail/assets/image_2.png
bread_mail/assets/image_3.png
bread_mail/assets/image_4.png
bread_mail/assets/logo.png