Metadata-Version: 2.1
Name: bread-mail
Version: 1.6
Summary: Email application
Home-page: UNKNOWN
Author: leox
Author-email: leox9611@gmail.com
License: UNKNOWN
Keywords: python,email
Platform: UNKNOWN
Classifier: Development Status :: 3 - Alpha
Classifier: Intended Audience :: Education
Classifier: Programming Language :: Python :: 2
Classifier: Programming Language :: Python :: 3
Classifier: Operating System :: MacOS :: MacOS X
Classifier: Operating System :: Microsoft :: Windows
